pacmimi/__init__.py
pacmimi/app_version.py
pacmimi/main.py
pacmimi/mirrorlist.py
pacmimi-1.1.2.dist-info/LICENSE
pacmimi-1.1.2.dist-info/METADATA
pacmimi-1.1.2.dist-info/WHEEL
pacmimi-1.1.2.dist-info/entry_points.txt
pacmimi-1.1.2.dist-info/top_level.txt
pacmimi-1.1.2.dist-info/RECORD
